portodjangostarter/__init__.py
portodjangostarter/_app_template/__init__.py
portodjangostarter/_app_template/actions/CreateAction.py-tpl
portodjangostarter/_app_template/admin.py-tpl
portodjangostarter/_app_template/apps.py-tpl
portodjangostarter/_app_template/management/__init__.py
portodjangostarter/_app_template/management/commands/__init__.py
portodjangostarter/_app_template/migrations/__init__.py
portodjangostarter/_app_template/models/__init__.py
portodjangostarter/_app_template/tasks/CreateTask.py-tpl
portodjangostarter/_app_template/tests/__init__.py
portodjangostarter/_app_template/ui/api/controllers/CreateController.py-tpl
portodjangostarter/_app_template/ui/api/routes/index.py-tpl
portodjangostarter/_app_template/ui/api/transformers/Transformer.py-tpl
portodjangostarter/asgi.py
portodjangostarter/management/__init__.py
portodjangostarter/management/commands/__init__.py
portodjangostarter/management/commands/startcontainer.py
portodjangostarter/settings.py
portodjangostarter/urls.py
portodjangostarter/wsgi.py
portodjangostarter-0.1.4.dist-info/WHEEL
portodjangostarter-0.1.4.dist-info/METADATA
portodjangostarter-0.1.4.dist-info/RECORD
