Metadata-Version: 2.1
Name: portodjangostarter
Version: 0.1.4
Summary: With portodjangostarter we can start porto containers in django project
Home-page: https://github.com/BakdauletBolat/portodjangostarter
Author: BakdauletBolat
Author-email: bakosh21345@gmail.com
Requires-Python: >=3.8,<4.0
Classifier: Programming Language :: Python :: 3
Classifier: Programming Language :: Python :: 3.10
Classifier: Programming Language :: Python :: 3.8
Classifier: Programming Language :: Python :: 3.9
Project-URL: Repository, https://github.com/BakdauletBolat/portodjangostarter
